ocrd_keraslm/__init__.py
ocrd_keraslm/lib/__init__.py
ocrd_keraslm/lib/callbacks.py
ocrd_keraslm/lib/rating.py
ocrd_keraslm/scripts/__init__.py
ocrd_keraslm/scripts/run.py
ocrd_keraslm/wrapper/__init__.py
ocrd_keraslm/wrapper/cli.py
ocrd_keraslm/wrapper/config.py
ocrd_keraslm/wrapper/ocrd-tool.json
ocrd_keraslm/wrapper/rate.py
ocrd_keraslm-0.4.3.dist-info/LICENSE
ocrd_keraslm-0.4.3.dist-info/METADATA
ocrd_keraslm-0.4.3.dist-info/WHEEL
ocrd_keraslm-0.4.3.dist-info/entry_points.txt
ocrd_keraslm-0.4.3.dist-info/top_level.txt
ocrd_keraslm-0.4.3.dist-info/RECORD
