Metadata-Version: 2.1
Name: ocrd_keraslm
Version: 0.4.3
Summary: character-level language modelling in Keras
Home-page: https://github.com/OCR-D/ocrd_keraslm
Author: Robert Sachunsky, Konstantin Baierer, Kay-Michael Würzner
Author-email: sachunsky@informatik.uni-leipzig.de, unixprog@gmail.com, wuerzner@gmail.com
License: Apache License 2.0
License-File: LICENSE
Requires-Dist: ocrd >=2.13.1
Requires-Dist: keras ==2.3.*
Requires-Dist: numpy <1.24
Requires-Dist: tensorflow-gpu ==1.15.*
Requires-Dist: protobuf <4.21
Requires-Dist: h5py ~=2.10
Requires-Dist: networkx >=2.0
Provides-Extra: plotting
Requires-Dist: sklearn ; extra == 'plotting'
Requires-Dist: matplotlib ; extra == 'plotting'
Requires-Dist: adjusttext ; extra == 'plotting'
